<edmx:Edmx xmlns:edmx="http://docs.oasis-open.org/odata/ns/edmx" Version="4.0">                                                                                                                                                                                
	<edmx:Reference Uri="http://docs.oasis-open.org/odata/odata-data-aggregation-ext/v4.0/cs02/vocabularies/Org.OData.Aggregation.V1.xml">                                                                                                                        
		<edmx:Include Alias="Aggregation" Namespace="Org.OData.Aggregation.V1"/>                                                                                                                                                                                     
	</edmx:Reference>                                                                                                                                                                                                                                             
	<edmx:Reference Uri="http://docs.oasis-open.org/odata/odata/v4.0/errata03/os/complete/vocabularies/Org.OData.Capabilities.V1.xml">                                                                                                                            
		<edmx:Include Alias="Capabilities" Namespace="Org.OData.Capabilities.V1"/>                                                                                                                                                                                   
	</edmx:Reference>                                                                                                                                                                                                                                             
	<edmx:Reference Uri="https://wiki.scn.sap.com/wiki/download/attachments/448470974/Common.xml?api=v2">                                                                                                                                                         
		<edmx:Include Alias="Common" Namespace="com.sap.vocabularies.Common.v1"/>                                                                                                                                                                                    
	</edmx:Reference>                                                                                                                                                                                                                                             
	<edmx:Reference Uri="https://wiki.scn.sap.com/wiki/download/attachments/448470971/Communication.xml?api=v2">                                                                                                                                                  
		<edmx:Include Alias="vCard" Namespace="com.sap.vocabularies.Communication.v1"/>                                                                                                                                                                              
	</edmx:Reference>                                                                                                                                                                                                                                             
	<edmx:Reference Uri="http://docs.oasis-open.org/odata/odata/v4.0/errata03/os/complete/vocabularies/Org.OData.Core.V1.xml">                                                                                                                                    
		<edmx:Include Alias="Core" Namespace="Org.OData.Core.V1"/>                                                                                                                                                                                                   
	</edmx:Reference>                                                                                                                                                                                                                                             
	<edmx:Reference Uri="http://docs.oasis-open.org/odata/odata/v4.0/errata03/os/complete/vocabularies/Org.OData.Measures.V1.xml">                                                                                                                                
		<edmx:Include Alias="CQP" Namespace="Org.OData.Measures.V1"/>                                                                                                                                                                                                
	</edmx:Reference>                                                                                                                                                                                                                                             
	<edmx:Reference Uri="https://wiki.scn.sap.com/wiki/download/attachments/448470968/UI.xml?api=v2">                                                                                                                                                             
		<edmx:Include Alias="UI" Namespace="com.sap.vocabularies.UI.v1"/>                                                                                                                                                                                            
	</edmx:Reference>                                                                                                                                                                                                                                             
	<edmx:DataServices>                                                                                                                                                                                                                                           
		<Schema xmlns="http://docs.oasis-open.org/odata/ns/edm">                                                                                                                                                                                                     
			<Annotations Target="ZGW_VENDOR_AGEING_SRV.VendorAgeing">                                                                                                                                                                                                   
				<Annotation Term="Aggregation.CustomAggregate">                                                                                                                                                                                                            
					<Apply Function="odata.concat">                                                                                                                                                                                                                           
						<Path>Period1</Path>                                                                                                                                                                                                                                     
						<Path>Period2</Path>                                                                                                                                                                                                                                     
					</Apply>                                                                                                                                                                                                                                                  
				</Annotation>                                                                                                                                                                                                                                              
				<Annotation Term="UI.LineItem">                                                                                                                                                                                                                            
					<Collection>                                                                                                                                                                                                                                              
						<Record Type="UI.DataField">                                                                                                                                                                                                                             
							<PropertyValue Property="Value" Path="Lifnr"/>                                                                                                                                                                                                          
							<PropertyValue Property="Label" String="{@i18n&gt;vendor_id}"/>                                                                                                                                                                                         
						</Record>                                                                                                                                                                                                                                                
						<Record Type="UI.DataField">                                                                                                                                                                                                                             
							<PropertyValue Property="Value" Path="Name1"/>                                                                                                                                                                                                          
							<PropertyValue Property="Label" String="{@i18n&gt;vendor_name}"/>                                                                                                                                                                                       
						</Record>                                                                                                                                                                                                                                                
						<Record Type="UI.DataField">                                                                                                                                                                                                                             
							<PropertyValue Property="Value" Path="Waers"/>                                                                                                                                                                                                          
							<PropertyValue Property="Label" String="{@i18n&gt;currency}"/>                                                                                                                                                                                          
						</Record>                                                                                                                                                                                                                                                
						<Record Type="UI.DataField">                                                                                                                                                                                                                             
							<PropertyValue Property="Value" Path="Opendate"/>                                                                                                                                                                                                       
							<PropertyValue Property="Label" String="{@i18n&gt;open_items}"/>                                                                                                                                                                                        
						</Record>                                                                                                                                                                                                                                                
						<Record Type="UI.DataField">                                                                                                                                                                                                                             
							<PropertyValue Property="Value" Path="Period1"/>                                                                                                                                                                                                        
							<PropertyValue Property="Label" String="{@i18n&gt;period1}"/>                                                                                                                                                                                           
						</Record>                                                                                                                                                                                                                                                
						<Record Type="UI.DataField">                                                                                                                                                                                                                             
							<PropertyValue Property="Value" Path="Period2"/>                                                                                                                                                                                                        
							<PropertyValue Property="Label" String="{@i18n&gt;period2}"/>                                                                                                                                                                                           
						</Record>                                                                                                                                                                                                                                                
						<Record Type="UI.DataField">                                                                                                                                                                                                                             
							<PropertyValue Property="Value" Path="Period3"/>                                                                                                                                                                                                        
							<PropertyValue Property="Label" String="{@i18n&gt;period3}"/>                                                                                                                                                                                           
						</Record>                                                                                                                                                                                                                                                
						<Record Type="UI.DataField">                                                                                                                                                                                                                             
							<PropertyValue Property="Value" Path="Period4"/>                                                                                                                                                                                                        
							<PropertyValue Property="Label" String="{@i18n&gt;period4}"/>                                                                                                                                                                                           
						</Record>                                                                                                                                                                                                                                                
						<Record Type="UI.DataField">                                                                                                                                                                                                                             
							<PropertyValue Property="Value" Path="Period5"/>                                                                                                                                                                                                        
							<PropertyValue Property="Label" String="{@i18n&gt;period5}"/>                                                                                                                                                                                           
						</Record>                                                                                                                                                                                                                                                
					</Collection>                                                                                                                                                                                                                                             
				</Annotation>                                                                                                                                                                                                                                              
			</Annotations>                                                                                                                                                                                                                                              
			<Annotations Target="ZGW_VENDOR_AGEING_SRV.VendorAgeingNoted">                                                                                                                                                                                              
				<Annotation Term="Aggregation.CustomAggregate">                                                                                                                                                                                                            
					<Apply Function="odata.concat">                                                                                                                                                                                                                           
						<Path>Period1</Path>                                                                                                                                                                                                                                     
						<Path>Period2</Path>                                                                                                                                                                                                                                     
					</Apply>                                                                                                                                                                                                                                                  
				</Annotation>                                                                                                                                                                                                                                              
				<Annotation Term="UI.LineItem">                                                                                                                                                                                                                            
					<Collection>                                                                                                                                                                                                                                              
						<Record Type="UI.DataField">                                                                                                                                                                                                                             
							<PropertyValue Property="Value" Path="Lifnr"/>                                                                                                                                                                                                          
							<PropertyValue Property="Label" String="{@i18n&gt;vendor_id}"/>                                                                                                                                                                                         
						</Record>                                                                                                                                                                                                                                                
						<Record Type="UI.DataField">                                                                                                                                                                                                                             
							<PropertyValue Property="Value" Path="Name1"/>                                                                                                                                                                                                          
							<PropertyValue Property="Label" String="{@i18n&gt;vendor_name}"/>                                                                                                                                                                                       
						</Record>                                                                                                                                                                                                                                                
						<Record Type="UI.DataField">                                                                                                                                                                                                                             
							<PropertyValue Property="Value" Path="Waers"/>                                                                                                                                                                                                          
							<PropertyValue Property="Label" String="{@i18n&gt;currency}"/>                                                                                                                                                                                          
						</Record>                                                                                                                                                                                                                                                
						<Record Type="UI.DataField">                                                                                                                                                                                                                             
							<PropertyValue Property="Value" Path="Opendate"/>                                                                                                                                                                                                       
							<PropertyValue Property="Label" String="{@i18n&gt;open_items}"/>                                                                                                                                                                                        
						</Record>                                                                                                                                                                                                                                                
						<Record Type="UI.DataField">                                                                                                                                                                                                                             
							<PropertyValue Property="Value" Path="Period1"/>                                                                                                                                                                                                        
							<PropertyValue Property="Label" String="{@i18n&gt;period1}"/>                                                                                                                                                                                           
						</Record>                                                                                                                                                                                                                                                
						<Record Type="UI.DataField">                                                                                                                                                                                                                             
							<PropertyValue Property="Value" Path="Period2"/>                                                                                                                                                                                                        
							<PropertyValue Property="Label" String="{@i18n&gt;period2}"/>                                                                                                                                                                                           
						</Record>                                                                                                                                                                                                                                                
						<Record Type="UI.DataField">                                                                                                                                                                                                                             
							<PropertyValue Property="Value" Path="Period3"/>                                                                                                                                                                                                        
							<PropertyValue Property="Label" String="{@i18n&gt;period3}"/>                                                                                                                                                                                           
						</Record>                                                                                                                                                                                                                                                
						<Record Type="UI.DataField">                                                                                                                                                                                                                             
							<PropertyValue Property="Value" Path="Period4"/>                                                                                                                                                                                                        
							<PropertyValue Property="Label" String="{@i18n&gt;period4}"/>                                                                                                                                                                                           
						</Record>                                                                                                                                                                                                                                                
						<Record Type="UI.DataField">                                                                                                                                                                                                                             
							<PropertyValue Property="Value" Path="Period5"/>                                                                                                                                                                                                        
							<PropertyValue Property="Label" String="{@i18n&gt;period5}"/>                                                                                                                                                                                           
						</Record>                                                                                                                                                                                                                                                
					</Collection>                                                                                                                                                                                                                                             
				</Annotation>                                                                                                                                                                                                                                              
			</Annotations>                                                                                                                                                                                                                                              
			<Annotations xmlns="http://docs.oasis-open.org/odata/ns/edm" Target="ZGW_VENDOR_AGEING_SRV.VendorAgeing/Bukrs">                                                                                                                                             
				<Annotation Term="com.sap.vocabularies.Common.v1.ValueList">                                                                                                                                                                                               
					<Record>                                                                                                                                                                                                                                                  
						<PropertyValue Property="Label" String="Company Code"/>                                                                                                                                                                                                  
						<PropertyValue Property="CollectionPath" String="DbuknSet"/>                                                                                                                                                                                             
						<PropertyValue Property="SearchSupported" Bool="true"/>                                                                                                                                                                                                  
						<PropertyValue Property="Parameters">                                                                                                                                                                                                                    
							<Collection>                                                                                                                                                                                                                                            
								<Record Type="com.sap.vocabularies.Common.v1.ValueListParameterInOut">                                                                                                                                                                                 
									<PropertyValue Property="LocalDataProperty" PropertyPath="Bukrs"/>                                                                                                                                                                                    
									<PropertyValue Property="ValueListProperty" String="Bukrs"/>                                                                                                                                                                                          
								</Record>                                                                                                                                                                                                                                              
								<Record Type="com.sap.vocabularies.Common.v1.ValueListParameterDisplayOnly">                                                                                                                                                                           
									<PropertyValue Property="ValueListProperty" String="Butxt"/>                                                                                                                                                                                          
								</Record>                                                                                                                                                                                                                                              
								<Record Type="com.sap.vocabularies.Common.v1.ValueListParameterDisplayOnly">                                                                                                                                                                           
									<PropertyValue Property="ValueListProperty" String="Ort01"/>                                                                                                                                                                                          
								</Record>                                                                                                                                                                                                                                              
								<Record Type="com.sap.vocabularies.Common.v1.ValueListParameterDisplayOnly">                                                                                                                                                                           
									<PropertyValue Property="ValueListProperty" String="Waers"/>                                                                                                                                                                                          
								</Record>                                                                                                                                                                                                                                              
							</Collection>                                                                                                                                                                                                                                           
						</PropertyValue>                                                                                                                                                                                                                                         
					</Record>                                                                                                                                                                                                                                                 
				</Annotation>                                                                                                                                                                                                                                              
			</Annotations>                                                                                                                                                                                                                                              
			<Annotations xmlns="http://docs.oasis-open.org/odata/ns/edm" Target="ZGW_VENDOR_AGEING_SRV.VendorAgeing/Lifnr">                                                                                                                                             
				<Annotation Term="com.sap.vocabularies.Common.v1.ValueList">                                                                                                                                                                                               
					<Record>                                                                                                                                                                                                                                                  
						<PropertyValue Property="Label" String="Supplier ID"/>                                                                                                                                                                                                   
						<PropertyValue Property="CollectionPath" String="KredkSet"/>                                                                                                                                                                                             
						<PropertyValue Property="SearchSupported" Bool="true"/>                                                                                                                                                                                                  
						<PropertyValue Property="Parameters">                                                                                                                                                                                                                    
							<Collection>                                                                                                                                                                                                                                            
								<Record Type="com.sap.vocabularies.Common.v1.ValueListParameterIn">                                                                                                                                                                                    
									<PropertyValue Property="LocalDataProperty" PropertyPath="Lifnr"/>                                                                                                                                                                                    
									<PropertyValue Property="ValueListProperty" String="Lifnr"/>                                                                                                                                                                                          
								</Record>                                                                                                                                                                                                                                              
								<Record Type="com.sap.vocabularies.Common.v1.ValueListParameterOut">                                                                                                                                                                                   
									<PropertyValue Property="LocalDataProperty" PropertyPath="Lifnr"/>                                                                                                                                                                                    
									<PropertyValue Property="ValueListProperty" String="Lifnr"/>                                                                                                                                                                                          
								</Record>                                                                                                                                                                                                                                              
								<Record Type="com.sap.vocabularies.Common.v1.ValueListParameterDisplayOnly">                                                                                                                                                                           
									<PropertyValue Property="ValueListProperty" String="Mcod1"/>                                                                                                                                                                                          
								</Record>                                                                                                                                                                                                                                              
								<Record Type="com.sap.vocabularies.Common.v1.ValueListParameterDisplayOnly">                                                                                                                                                                           
									<PropertyValue Property="ValueListProperty" String="Bukrs"/>                                                                                                                                                                                          
								</Record>                                                                                                                                                                                                                                              
								<Record Type="com.sap.vocabularies.Common.v1.ValueListParameterDisplayOnly">                                                                                                                                                                           
									<PropertyValue Property="ValueListProperty" String="Mcod3"/>                                                                                                                                                                                          
								</Record>                                                                                                                                                                                                                                              
								<Record Type="com.sap.vocabularies.Common.v1.ValueListParameterDisplayOnly">                                                                                                                                                                           
									<PropertyValue Property="ValueListProperty" String="Pstlz"/>                                                                                                                                                                                          
								</Record>                                                                                                                                                                                                                                              
								<Record Type="com.sap.vocabularies.Common.v1.ValueListParameterDisplayOnly">                                                                                                                                                                           
									<PropertyValue Property="ValueListProperty" String="Land1"/>                                                                                                                                                                                          
								</Record>                                                                                                                                                                                                                                              
							</Collection>                                                                                                                                                                                                                                           
						</PropertyValue>                                                                                                                                                                                                                                         
					</Record>                                                                                                                                                                                                                                                 
				</Annotation>                                                                                                                                                                                                                                              
			</Annotations>                                                                                                                                                                                                                                              
		</Schema>                                                                                                                                                                                                                                                    
	</edmx:DataServices>                                                                                                                                                                                                                                          
</edmx:Edmx>                                                                                                                                                                                                                                                   